{
  "wall_time_s": 2952.387535151007,
  "audio_path": "output/Elke_Best_restored_run18.wav",
  "mode": "restoration",
  "effective_quality_mode": "quality",
  "effective_is_studio_2026": false,
  "checkpoints": [
    {
      "phase_id": "phase_05_rumble_filter",
      "wall_time_s": 1779052175.4031348,
      "musical_goals": {
        "brillanz": 0.4919050727679342,
        "waerme": 0.971880905103586,
        "groove": 0.4998151322777393,
        "tonal_center": 1.0,
        "natuerlichkeit": 0.894985940002984,
        "timbre_authentizitaet": 0.928504400127132,
        "bass_kraft": 1.0,
        "authentizitaet": 0.9456817074403607,
        "emotionalitaet": 0.4124055847796507,
        "transparenz": 0.8578099747422068,
        "spatial_depth": 0.9209680108053895,
        "micro_dynamics": 0.9429999999999996,
        "separation_fidelity": 0.898187423225248,
        "artikulation": 0.9239999999999996
      },
      "hpi_score": 0.2601,
      "artifact_freedom": 1.0,
      "carrier_recovery_ratio": 0.15509126412270757,
      "noise_floor_db": null,
      "defects_remaining": null,
      "anomalies": [],
      "pegelexplosion_detected": false,
      "pegelexplosion_severity": "none",
      "pegelexplosion_cause": null
    },
    {
      "phase_id": "phase_04_eq_correction",
      "wall_time_s": 1779052187.7699068,
      "musical_goals": {
        "brillanz": 0.4919068501796379,
        "waerme": 0.9718809038599541,
        "groove": 0.49981513237498193,
        "tonal_center": 1.0,
        "natuerlichkeit": 1.0,
        "timbre_authentizitaet": 1.0,
        "bass_kraft": 1.0,
        "authentizitaet": 1.0,
        "emotionalitaet": 0.5769271028427916,
        "transparenz": 0.8578098264163339,
        "spatial_depth": 0.9209680147969718,
        "micro_dynamics": 0.9429999999999996,
        "separation_fidelity": 0.8349999995723657,
        "artikulation": 0.9239999999379092
      },
      "hpi_score": 0.2601,
      "artifact_freedom": 1.0,
      "carrier_recovery_ratio": 0.15509126412270757,
      "noise_floor_db": null,
      "defects_remaining": null,
      "anomalies": [],
      "pegelexplosion_detected": false,
      "pegelexplosion_severity": "none",
      "pegelexplosion_cause": null
    },
    {
      "phase_id": "phase_01_click_removal",
      "wall_time_s": 1779052200.6972125,
      "musical_goals": {
        "brillanz": 0.4919069053993596,
        "waerme": 0.9718809038599541,
        "groove": 0.49981452538059395,
        "tonal_center": 1.0,
        "natuerlichkeit": 1.0,
        "timbre_authentizitaet": 1.0,
        "bass_kraft": 1.0,
        "authentizitaet": 1.0,
        "emotionalitaet": 0.5767526502410392,
        "transparenz": 0.8578098295724343,
        "spatial_depth": 0.9210296509597875,
        "micro_dynamics": 0.9429999999999996,
        "separation_fidelity": 0.8349999995723794,
        "artikulation": 0.9239999983401699
      },
      "hpi_score": 0.2601,
      "artifact_freedom": 1.0,
      "carrier_recovery_ratio": 0.15509126412270757,
      "noise_floor_db": null,
      "defects_remaining": null,
      "anomalies": [],
      "pegelexplosion_detected": false,
      "pegelexplosion_severity": "none",
      "pegelexplosion_cause": null
    },
    {
      "phase_id": "phase_12_wow_flutter_fix",
      "wall_time_s": 1779052208.223972,
      "musical_goals": {
        "brillanz": 0.4919069053993596,
        "waerme": 0.9718809038599541,
        "groove": 0.49981452538059395,
        "tonal_center": 1.0,
        "natuerlichkeit": 1.0,
        "timbre_authentizitaet": 1.0,
        "bass_kraft": 1.0,
        "authentizitaet": 1.0,
        "emotionalitaet": 0.5767526502410392,
        "transparenz": 0.8578098295724343,
        "spatial_depth": 0.9210296509597875,
        "micro_dynamics": 0.9429999999999996,
        "separation_fidelity": 0.8349999995723794,
        "artikulation": 0.9239999983401699
      },
      "hpi_score": 0.2601,
      "artifact_freedom": 1.0,
      "carrier_recovery_ratio": 0.15509126412270757,
      "noise_floor_db": null,
      "defects_remaining": null,
      "anomalies": [],
      "pegelexplosion_detected": false,
      "pegelexplosion_severity": "none",
      "pegelexplosion_cause": null
    },
    {
      "phase_id": "phase_24_dropout_repair",
      "wall_time_s": 1779052373.0662153,
      "musical_goals": {
        "brillanz": 0.4934559503278952,
        "waerme": 0.9718133174575856,
        "groove": 0.499814464222864,
        "tonal_center": 1.0,
        "natuerlichkeit": 1.0,
        "timbre_authentizitaet": 0.9673899147760046,
        "bass_kraft": 1.0,
        "authentizitaet": 1.0,
        "emotionalitaet": 0.5764345352985633,
        "transparenz": 0.8575024388081237,
        "spatial_depth": 0.9191921597474987,
        "micro_dynamics": 0.9429999999999996,
        "separation_fidelity": 0.8277967731365061,
        "artikulation": 0.9239936402714259
      },
      "hpi_score": 0.2601,
      "artifact_freedom": 1.0,
      "carrier_recovery_ratio": 0.15509126412270757,
      "noise_floor_db": null,
      "defects_remaining": null,
      "anomalies": [],
      "pegelexplosion_detected": false,
      "pegelexplosion_severity": "none",
      "pegelexplosion_cause": null
    },
    {
      "phase_id": "phase_55_diffusion_inpainting",
      "wall_time_s": 1779052406.5016692,
      "musical_goals": {
        "brillanz": 0.4934559503278952,
        "waerme": 0.9718133174575856,
        "groove": 0.499814464222864,
        "tonal_center": 1.0,
        "natuerlichkeit": 1.0,
        "timbre_authentizitaet": 0.9673899147760046,
        "bass_kraft": 1.0,
        "authentizitaet": 1.0,
        "emotionalitaet": 0.5764345352985633,
        "transparenz": 0.8575024388081237,
        "spatial_depth": 0.9191921597474987,
        "micro_dynamics": 0.9429999999999996,
        "separation_fidelity": 0.8277967731365061,
        "artikulation": 0.9239936402714259
      },
      "hpi_score": 0.2601,
      "artifact_freedom": 1.0,
      "carrier_recovery_ratio": 0.15509126412270757,
      "noise_floor_db": null,
      "defects_remaining": null,
      "anomalies": [],
      "pegelexplosion_detected": false,
      "pegelexplosion_severity": "none",
      "pegelexplosion_cause": null
    },
    {
      "phase_id": "phase_23_spectral_repair",
      "wall_time_s": 1779052559.5690677,
      "musical_goals": {
        "brillanz": 0.5541004004434339,
        "waerme": 0.9678006009097525,
        "groove": 0.49987373937935964,
        "tonal_center": 1.0,
        "natuerlichkeit": 1.0,
        "timbre_authentizitaet": 0.9532876872997801,
        "bass_kraft": 1.0,
        "authentizitaet": 1.0,
        "emotionalitaet": 0.5849276802281415,
        "transparenz": 0.846672298004479,
        "spatial_depth": 0.9518341774358999,
        "micro_dynamics": 0.9429999999999996,
        "separation_fidelity": 0.822453522321531,
        "artikulation": 0.9234047537092902
      },
      "hpi_score": 0.2601,
      "artifact_freedom": 1.0,
      "carrier_recovery_ratio": 0.15509126412270757,
      "noise_floor_db": null,
      "defects_remaining": null,
      "anomalies": [],
      "pegelexplosion_detected": false,
      "pegelexplosion_severity": "none",
      "pegelexplosion_cause": null
    },
    {
      "phase_id": "phase_50_spectral_repair",
      "wall_time_s": 1779052650.3032603,
      "musical_goals": {
        "brillanz": 0.5604776433108071,
        "waerme": 0.9675025196464688,
        "groove": 0.4998737504328219,
        "tonal_center": 1.0,
        "natuerlichkeit": 1.0,
        "timbre_authentizitaet": 1.0,
        "bass_kraft": 1.0,
        "authentizitaet": 1.0,
        "emotionalitaet": 0.6067115561358829,
        "transparenz": 0.8455608698413928,
        "spatial_depth": 0.9518487229816454,
        "micro_dynamics": 0.9429999999999996,
        "separation_fidelity": 0.8146838406525334,
        "artikulation": 0.9239914725060803
      },
      "hpi_score": 0.2601,
      "artifact_freedom": 1.0,
      "carrier_recovery_ratio": 0.15509126412270757,
      "noise_floor_db": null,
      "defects_remaining": null,
      "anomalies": [],
      "pegelexplosion_detected": false,
      "pegelexplosion_severity": "none",
      "pegelexplosion_cause": null
    },
    {
      "phase_id": "phase_09_crackle_removal",
      "wall_time_s": 1779052689.9613914,
      "musical_goals": {
        "brillanz": 0.5604776433108071,
        "waerme": 0.9675025196464688,
        "groove": 0.4998737504328219,
        "tonal_center": 1.0,
        "natuerlichkeit": 1.0,
        "timbre_authentizitaet": 1.0,
        "bass_kraft": 1.0,
        "authentizitaet": 1.0,
        "emotionalitaet": 0.6067115561358829,
        "transparenz": 0.8455608698413928,
        "spatial_depth": 0.9518487229816454,
        "micro_dynamics": 0.9429999999999996,
        "separation_fidelity": 0.8146838406525334,
        "artikulation": 0.9239914725060803
      },
      "hpi_score": 0.2601,
      "artifact_freedom": 1.0,
      "carrier_recovery_ratio": 0.15509126412270757,
      "noise_floor_db": null,
      "defects_remaining": null,
      "anomalies": [],
      "pegelexplosion_detected": false,
      "pegelexplosion_severity": "none",
      "pegelexplosion_cause": null
    },
    {
      "phase_id": "phase_60_inner_groove_distortion_repair",
      "wall_time_s": 1779052705.4307687,
      "musical_goals": {
        "brillanz": 0.5604775945502901,
        "waerme": 0.9675025196464688,
        "groove": 0.4998737504406815,
        "tonal_center": 1.0,
        "natuerlichkeit": 1.0,
        "timbre_authentizitaet": 1.0,
        "bass_kraft": 1.0,
        "authentizitaet": 1.0,
        "emotionalitaet": 0.6067133028441276,
        "transparenz": 0.8455608698413928,
        "spatial_depth": 0.9518487229816454,
        "micro_dynamics": 0.9429999999999996,
        "separation_fidelity": 0.8349999999040437,
        "artikulation": 0.9239999985741153
      },
      "hpi_score": 0.2601,
      "artifact_freedom": 1.0,
      "carrier_recovery_ratio": 0.15509126412270757,
      "noise_floor_db": null,
      "defects_remaining": null,
      "anomalies": [],
      "pegelexplosion_detected": false,
      "pegelexplosion_severity": "none",
      "pegelexplosion_cause": null
    },
    {
      "phase_id": "phase_61_groove_echo_cancellation",
      "wall_time_s": 1779052716.6282244,
      "musical_goals": {
        "brillanz": 0.5604775945502901,
        "waerme": 0.9675025196464688,
        "groove": 0.4998737504406815,
        "tonal_center": 1.0,
        "natuerlichkeit": 1.0,
        "timbre_authentizitaet": 1.0,
        "bass_kraft": 1.0,
        "authentizitaet": 1.0,
        "emotionalitaet": 0.6067133028441276,
        "transparenz": 0.8455608698413928,
        "spatial_depth": 0.9518487229816454,
        "micro_dynamics": 0.9429999999999996,
        "separation_fidelity": 0.8349999999040437,
        "artikulation": 0.9239999985741153
      },
      "hpi_score": 0.2601,
      "artifact_freedom": 1.0,
      "carrier_recovery_ratio": 0.15509126412270757,
      "noise_floor_db": null,
      "defects_remaining": null,
      "anomalies": [],
      "pegelexplosion_detected": false,
      "pegelexplosion_severity": "none",
      "pegelexplosion_cause": null
    },
    {
      "phase_id": "phase_29_tape_hiss_reduction",
      "wall_time_s": 1779052809.8658733,
      "musical_goals": {
        "brillanz": 1.0,
        "waerme": 0.25748693128409433,
        "groove": 0.4956904958495467,
        "tonal_center": 1.0,
        "natuerlichkeit": 0.7341844474527659,
        "timbre_authentizitaet": 0.5090920910572753,
        "bass_kraft": 1.0,
        "authentizitaet": 0.008639670891952467,
        "emotionalitaet": 0.19400956032866495,
        "transparenz": 0.0,
        "spatial_depth": 0.7930200208611741,
        "micro_dynamics": 0.9248701442437255,
        "separation_fidelity": 0.8058279043487379,
        "artikulation": 0.8988066559343131
      },
      "hpi_score": 0.2601,
      "artifact_freedom": 1.0,
      "carrier_recovery_ratio": 0.15509126412270757,
      "noise_floor_db": null,
      "defects_remaining": null,
      "anomalies": [
        "waerme: 0.97 \u2192 0.26 (\u0394=-0.71)",
        "natuerlichkeit: 1.00 \u2192 0.73 (\u0394=-0.27)",
        "timbre_authentizitaet: 1.00 \u2192 0.51 (\u0394=-0.49)",
        "authentizitaet: 1.00 \u2192 0.01 (\u0394=-0.99)",
        "emotionalitaet: 0.61 \u2192 0.19 (\u0394=-0.41)",
        "transparenz: 0.85 \u2192 0.00 (\u0394=-0.85)",
        "spatial_depth: 0.95 \u2192 0.79 (\u0394=-0.16)",
        "PMGG best_effort: best_effort"
      ],
      "pegelexplosion_detected": false,
      "pegelexplosion_severity": "none",
      "pegelexplosion_cause": null
    },
    {
      "phase_id": "phase_27_click_pop_removal",
      "wall_time_s": 1779052902.1808412,
      "musical_goals": {
        "brillanz": 0.5618669138812848,
        "waerme": 0.9674562209390526,
        "groove": 0.49987723657125144,
        "tonal_center": 1.0,
        "natuerlichkeit": 1.0,
        "timbre_authentizitaet": 1.0,
        "bass_kraft": 1.0,
        "authentizitaet": 1.0,
        "emotionalitaet": 0.6064741562001938,
        "transparenz": 0.8453662271966969,
        "spatial_depth": 0.9527629169107427,
        "micro_dynamics": 0.9429999999999996,
        "separation_fidelity": 0.8349509107356108,
        "artikulation": 0.9239963502477256
      },
      "hpi_score": 0.2601,
      "artifact_freedom": 1.0,
      "carrier_recovery_ratio": 0.15509126412270757,
      "noise_floor_db": null,
      "defects_remaining": null,
      "anomalies": [
        "brillanz: 1.00 \u2192 0.56 (\u0394=-0.44)"
      ],
      "pegelexplosion_detected": false,
      "pegelexplosion_severity": "none",
      "pegelexplosion_cause": null
    },
    {
      "phase_id": "phase_02_hum_removal",
      "wall_time_s": 1779052961.7153597,
      "musical_goals": {
        "brillanz": 0.5618669138812848,
        "waerme": 0.9674562209390526,
        "groove": 0.49987701758519604,
        "tonal_center": 1.0,
        "natuerlichkeit": 1.0,
        "timbre_authentizitaet": 1.0,
        "bass_kraft": 1.0,
        "authentizitaet": 1.0,
        "emotionalitaet": 0.6066825043782286,
        "transparenz": 0.8453662271966969,
        "spatial_depth": 0.9527513758185846,
        "micro_dynamics": 0.9429999999999996,
        "separation_fidelity": 0.8141332633495812,
        "artikulation": 0.9239994821430758
      },
      "hpi_score": 0.2601,
      "artifact_freedom": 1.0,
      "carrier_recovery_ratio": 0.15509126412270757,
      "noise_floor_db": null,
      "defects_remaining": null,
      "anomalies": [],
      "pegelexplosion_detected": false,
      "pegelexplosion_severity": "none",
      "pegelexplosion_cause": null
    },
    {
      "phase_id": "phase_03_denoise",
      "wall_time_s": 1779053060.5748963,
      "musical_goals": {
        "brillanz": 0.5641734177842456,
        "waerme": 0.9667588469017089,
        "groove": 0.49986149971223115,
        "tonal_center": 1.0,
        "natuerlichkeit": 1.0,
        "timbre_authentizitaet": 1.0,
        "bass_kraft": 1.0,
        "authentizitaet": 1.0,
        "emotionalitaet": 0.6077415528721076,
        "transparenz": 0.8418677838208728,
        "spatial_depth": 0.989775647086164,
        "micro_dynamics": 0.9429999999999996,
        "separation_fidelity": 0.8247690489494729,
        "artikulation": 0.923993552811729
      },
      "hpi_score": 0.2601,
      "artifact_freedom": 1.0,
      "carrier_recovery_ratio": 0.15509126412270757,
      "noise_floor_db": null,
      "defects_remaining": null,
      "anomalies": [],
      "pegelexplosion_detected": false,
      "pegelexplosion_severity": "none",
      "pegelexplosion_cause": null
    },
    {
      "phase_id": "phase_18_noise_gate",
      "wall_time_s": 1779053095.4605362,
      "musical_goals": {
        "brillanz": 0.5676982738423195,
        "waerme": 0.9665785831184107,
        "groove": 0.4998614586415894,
        "tonal_center": 1.0,
        "natuerlichkeit": 1.0,
        "timbre_authentizitaet": 1.0,
        "bass_kraft": 1.0,
        "authentizitaet": 1.0,
        "emotionalitaet": 0.6084079361665357,
        "transparenz": 0.841070325343555,
        "spatial_depth": 0.9890233289303502,
        "micro_dynamics": 0.9429999999999996,
        "separation_fidelity": 0.8224573862006538,
        "artikulation": 0.9239977754054028
      },
      "hpi_score": 0.2601,
      "artifact_freedom": 1.0,
      "carrier_recovery_ratio": 0.15509126412270757,
      "noise_floor_db": null,
      "defects_remaining": null,
      "anomalies": [],
      "pegelexplosion_detected": false,
      "pegelexplosion_severity": "none",
      "pegelexplosion_cause": null
    },
    {
      "phase_id": "phase_31_speed_pitch_correction",
      "wall_time_s": 1779053112.119635,
      "musical_goals": {
        "brillanz": 0.5676982738423195,
        "waerme": 0.9665785831184107,
        "groove": 0.4998614586415894,
        "tonal_center": 1.0,
        "natuerlichkeit": 1.0,
        "timbre_authentizitaet": 1.0,
        "bass_kraft": 1.0,
        "authentizitaet": 1.0,
        "emotionalitaet": 0.6084079361665357,
        "transparenz": 0.841070325343555,
        "spatial_depth": 0.9890233289303502,
        "micro_dynamics": 0.9429999999999996,
        "separation_fidelity": 0.8224573862006538,
        "artikulation": 0.9239977754054028
      },
      "hpi_score": 0.2601,
      "artifact_freedom": 1.0,
      "carrier_recovery_ratio": 0.15509126412270757,
      "noise_floor_db": null,
      "defects_remaining": null,
      "anomalies": [],
      "pegelexplosion_detected": false,
      "pegelexplosion_severity": "none",
      "pegelexplosion_cause": null
    },
    {
      "phase_id": "phase_14_phase_correction",
      "wall_time_s": 1779053120.4375207,
      "musical_goals": {
        "brillanz": 0.5676982738423195,
        "waerme": 0.9665785831184107,
        "groove": 0.4998614586415894,
        "tonal_center": 1.0,
        "natuerlichkeit": 1.0,
        "timbre_authentizitaet": 1.0,
        "bass_kraft": 1.0,
        "authentizitaet": 1.0,
        "emotionalitaet": 0.6084079361665357,
        "transparenz": 0.841070325343555,
        "spatial_depth": 0.9890233289303502,
        "micro_dynamics": 0.9429999999999996,
        "separation_fidelity": 0.8224573862006538,
        "artikulation": 0.9239977754054028
      },
      "hpi_score": 0.2601,
      "artifact_freedom": 1.0,
      "carrier_recovery_ratio": 0.15509126412270757,
      "noise_floor_db": null,
      "defects_remaining": null,
      "anomalies": [],
      "pegelexplosion_detected": false,
      "pegelexplosion_severity": "none",
      "pegelexplosion_cause": null
    },
    {
      "phase_id": "phase_49_advanced_dereverb",
      "wall_time_s": 1779053126.598043,
      "musical_goals": {
        "brillanz": 0.5676982738423195,
        "waerme": 0.9665785831184107,
        "groove": 0.4998614586415894,
        "tonal_center": 1.0,
        "natuerlichkeit": 1.0,
        "timbre_authentizitaet": 1.0,
        "bass_kraft": 1.0,
        "authentizitaet": 1.0,
        "emotionalitaet": 0.6084079361665357,
        "transparenz": 0.841070325343555,
        "spatial_depth": 0.9890233289303502,
        "micro_dynamics": 0.9429999999999996,
        "separation_fidelity": 0.8224573862006538,
        "artikulation": 0.9239977754054028
      },
      "hpi_score": 0.2601,
      "artifact_freedom": 1.0,
      "carrier_recovery_ratio": 0.15509126412270757,
      "noise_floor_db": null,
      "defects_remaining": null,
      "anomalies": [],
      "pegelexplosion_detected": false,
      "pegelexplosion_severity": "none",
      "pegelexplosion_cause": null
    },
    {
      "phase_id": "phase_26_dynamic_range_expansion",
      "wall_time_s": 1779053140.1608648,
      "musical_goals": {
        "brillanz": 0.5643773069402763,
        "waerme": 0.9668282508218955,
        "groove": 0.4998614499570503,
        "tonal_center": 1.0,
        "natuerlichkeit": 1.0,
        "timbre_authentizitaet": 1.0,
        "bass_kraft": 1.0,
        "authentizitaet": 1.0,
        "emotionalitaet": 0.6085577258966971,
        "transparenz": 0.8420034700091442,
        "spatial_depth": 0.9889089972142084,
        "micro_dynamics": 0.9429999999999996,
        "separation_fidelity": 0.8263619036756079,
        "artikulation": 0.9239999091969826
      },
      "hpi_score": 0.2601,
      "artifact_freedom": 1.0,
      "carrier_recovery_ratio": 0.15509126412270757,
      "noise_floor_db": null,
      "defects_remaining": null,
      "anomalies": [],
      "pegelexplosion_detected": false,
      "pegelexplosion_severity": "none",
      "pegelexplosion_cause": null
    },
    {
      "phase_id": "phase_08_transient_preservation",
      "wall_time_s": 1779053160.272651,
      "musical_goals": {
        "brillanz": 0.5621865781096631,
        "waerme": 0.9668901119250739,
        "groove": 0.49986116966092353,
        "tonal_center": 1.0,
        "natuerlichkeit": 1.0,
        "timbre_authentizitaet": 1.0,
        "bass_kraft": 1.0,
        "authentizitaet": 1.0,
        "emotionalitaet": 0.6086024601903989,
        "transparenz": 0.8422266825158853,
        "spatial_depth": 0.9888937734714153,
        "micro_dynamics": 0.9429999999999996,
        "separation_fidelity": 0.82288599737501,
        "artikulation": 0.923999930952948
      },
      "hpi_score": 0.2601,
      "artifact_freedom": 1.0,
      "carrier_recovery_ratio": 0.15509126412270757,
      "noise_floor_db": null,
      "defects_remaining": null,
      "anomalies": [],
      "pegelexplosion_detected": false,
      "pegelexplosion_severity": "none",
      "pegelexplosion_cause": null
    },
    {
      "phase_id": "phase_36_transient_shaper",
      "wall_time_s": 1779053385.256529,
      "musical_goals": {
        "brillanz": 0.5624477199835335,
        "waerme": 0.9668537352153151,
        "groove": 0.4998625204354161,
        "tonal_center": 1.0,
        "natuerlichkeit": 1.0,
        "timbre_authentizitaet": 1.0,
        "bass_kraft": 1.0,
        "authentizitaet": 1.0,
        "emotionalitaet": 0.6087639864827463,
        "transparenz": 0.8420032783535798,
        "spatial_depth": 0.9891902484444703,
        "micro_dynamics": 0.9429999999999996,
        "separation_fidelity": 0.8264791683391199,
        "artikulation": 0.9239999623855829
      },
      "hpi_score": 0.2601,
      "artifact_freedom": 1.0,
      "carrier_recovery_ratio": 0.15509126412270757,
      "noise_floor_db": null,
      "defects_remaining": null,
      "anomalies": [],
      "pegelexplosion_detected": false,
      "pegelexplosion_severity": "none",
      "pegelexplosion_cause": null
    },
    {
      "phase_id": "phase_19_de_esser",
      "wall_time_s": 1779053529.6382012,
      "musical_goals": {
        "brillanz": 0.5912603442099348,
        "waerme": 0.9668006205821992,
        "groove": 0.4998417942869869,
        "tonal_center": 1.0,
        "natuerlichkeit": 1.0,
        "timbre_authentizitaet": 1.0,
        "bass_kraft": 1.0,
        "authentizitaet": 1.0,
        "emotionalitaet": 0.6042278183777141,
        "transparenz": 0.8393559465349109,
        "spatial_depth": 0.9922911550060497,
        "micro_dynamics": 0.9429999999999996,
        "separation_fidelity": 0.8216412953613736,
        "artikulation": 0.923994487443206
      },
      "hpi_score": 0.2601,
      "artifact_freedom": 1.0,
      "carrier_recovery_ratio": 0.15509126412270757,
      "noise_floor_db": null,
      "defects_remaining": null,
      "anomalies": [],
      "pegelexplosion_detected": false,
      "pegelexplosion_severity": "none",
      "pegelexplosion_cause": null
    },
    {
      "phase_id": "phase_43_ml_deesser",
      "wall_time_s": 1779053548.6002247,
      "musical_goals": {
        "brillanz": 0.5912603442099348,
        "waerme": 0.9668006205821992,
        "groove": 0.4998417942870032,
        "tonal_center": 1.0,
        "natuerlichkeit": 1.0,
        "timbre_authentizitaet": 1.0,
        "bass_kraft": 1.0,
        "authentizitaet": 1.0,
        "emotionalitaet": 0.6046642858802903,
        "transparenz": 0.8393559465349109,
        "spatial_depth": 0.9922910779444475,
        "micro_dynamics": 0.9429999999999996,
        "separation_fidelity": 0.8349999998928956,
        "artikulation": 0.9239999990494558
      },
      "hpi_score": 0.2601,
      "artifact_freedom": 1.0,
      "carrier_recovery_ratio": 0.15509126412270757,
      "noise_floor_db": null,
      "defects_remaining": null,
      "anomalies": [],
      "pegelexplosion_detected": false,
      "pegelexplosion_severity": "none",
      "pegelexplosion_cause": null
    },
    {
      "phase_id": "phase_06_frequency_restoration",
      "wall_time_s": 1779054057.9019918,
      "musical_goals": {
        "brillanz": 0.5912603442099348,
        "waerme": 0.9668006205821992,
        "groove": 0.4998417942870032,
        "tonal_center": 1.0,
        "natuerlichkeit": 1.0,
        "timbre_authentizitaet": 1.0,
        "bass_kraft": 1.0,
        "authentizitaet": 1.0,
        "emotionalitaet": 0.6046642858802903,
        "transparenz": 0.8393559465349109,
        "spatial_depth": 0.9922910779444475,
        "micro_dynamics": 0.9429999999999996,
        "separation_fidelity": 0.8349999998928956,
        "artikulation": 0.9239999990494558
      },
      "hpi_score": 0.2601,
      "artifact_freedom": 1.0,
      "carrier_recovery_ratio": 0.15509126412270757,
      "noise_floor_db": null,
      "defects_remaining": null,
      "anomalies": [],
      "pegelexplosion_detected": false,
      "pegelexplosion_severity": "none",
      "pegelexplosion_cause": null
    },
    {
      "phase_id": "phase_07_harmonic_restoration",
      "wall_time_s": 1779054068.0408156,
      "musical_goals": {
        "brillanz": 0.5912603442099348,
        "waerme": 0.9668006205821992,
        "groove": 0.4998417942870032,
        "tonal_center": 1.0,
        "natuerlichkeit": 1.0,
        "timbre_authentizitaet": 1.0,
        "bass_kraft": 1.0,
        "authentizitaet": 1.0,
        "emotionalitaet": 0.6046642858802903,
        "transparenz": 0.8393559465349109,
        "spatial_depth": 0.9922910779444475,
        "micro_dynamics": 0.9429999999999996,
        "separation_fidelity": 0.8349999998928956,
        "artikulation": 0.9239999990494558
      },
      "hpi_score": 0.2601,
      "artifact_freedom": 1.0,
      "carrier_recovery_ratio": 0.15509126412270757,
      "noise_floor_db": null,
      "defects_remaining": null,
      "anomalies": [],
      "pegelexplosion_detected": false,
      "pegelexplosion_severity": "none",
      "pegelexplosion_cause": null
    },
    {
      "phase_id": "phase_59_modulation_noise_reduction",
      "wall_time_s": 1779054088.4461868,
      "musical_goals": {
        "brillanz": 0.5912603442099348,
        "waerme": 0.9668006205821992,
        "groove": 0.4998417942889597,
        "tonal_center": 1.0,
        "natuerlichkeit": 1.0,
        "timbre_authentizitaet": 1.0,
        "bass_kraft": 1.0,
        "authentizitaet": 1.0,
        "emotionalitaet": 0.604664281936839,
        "transparenz": 0.8393559465349109,
        "spatial_depth": 0.9922910779444475,
        "micro_dynamics": 0.9429999999999996,
        "separation_fidelity": 0.8349999998928956,
        "artikulation": 0.9239999990171086
      },
      "hpi_score": 0.2601,
      "artifact_freedom": 1.0,
      "carrier_recovery_ratio": 0.15509126412270757,
      "noise_floor_db": null,
      "defects_remaining": null,
      "anomalies": [],
      "pegelexplosion_detected": false,
      "pegelexplosion_severity": "none",
      "pegelexplosion_cause": null
    },
    {
      "phase_id": "phase_62_crosstalk_cancellation",
      "wall_time_s": 1779054099.3944697,
      "musical_goals": {
        "brillanz": 0.5912603442099348,
        "waerme": 0.9668006205821992,
        "groove": 0.4998417942889597,
        "tonal_center": 1.0,
        "natuerlichkeit": 1.0,
        "timbre_authentizitaet": 1.0,
        "bass_kraft": 1.0,
        "authentizitaet": 1.0,
        "emotionalitaet": 0.604664281936839,
        "transparenz": 0.8393559465349109,
        "spatial_depth": 0.9922910779444475,
        "micro_dynamics": 0.9429999999999996,
        "separation_fidelity": 0.8349999998928956,
        "artikulation": 0.9239999990171086
      },
      "hpi_score": 0.2601,
      "artifact_freedom": 1.0,
      "carrier_recovery_ratio": 0.15509126412270757,
      "noise_floor_db": null,
      "defects_remaining": null,
      "anomalies": [],
      "pegelexplosion_detected": false,
      "pegelexplosion_severity": "none",
      "pegelexplosion_cause": null
    },
    {
      "phase_id": "phase_39_air_band_enhancement",
      "wall_time_s": 1779054105.1632957,
      "musical_goals": {
        "brillanz": 0.5912603442099348,
        "waerme": 0.9668006205821992,
        "groove": 0.4998417942889597,
        "tonal_center": 1.0,
        "natuerlichkeit": 1.0,
        "timbre_authentizitaet": 1.0,
        "bass_kraft": 1.0,
        "authentizitaet": 1.0,
        "emotionalitaet": 0.604664281936839,
        "transparenz": 0.8393559465349109,
        "spatial_depth": 0.9922910779444475,
        "micro_dynamics": 0.9429999999999996,
        "separation_fidelity": 0.8349999998928956,
        "artikulation": 0.9239999990171086
      },
      "hpi_score": 0.2601,
      "artifact_freedom": 1.0,
      "carrier_recovery_ratio": 0.15509126412270757,
      "noise_floor_db": null,
      "defects_remaining": null,
      "anomalies": [],
      "pegelexplosion_detected": false,
      "pegelexplosion_severity": "none",
      "pegelexplosion_cause": null
    },
    {
      "phase_id": "phase_34_mid_side_processing",
      "wall_time_s": 1779054115.1309392,
      "musical_goals": {
        "brillanz": 0.5912603442099348,
        "waerme": 0.9668006205821992,
        "groove": 0.4998417942889597,
        "tonal_center": 1.0,
        "natuerlichkeit": 1.0,
        "timbre_authentizitaet": 1.0,
        "bass_kraft": 1.0,
        "authentizitaet": 1.0,
        "emotionalitaet": 0.604664281936839,
        "transparenz": 0.8393559465349109,
        "spatial_depth": 0.9922910779444475,
        "micro_dynamics": 0.9429999999999996,
        "separation_fidelity": 0.8349999998928956,
        "artikulation": 0.9239999990171086
      },
      "hpi_score": 0.2601,
      "artifact_freedom": 1.0,
      "carrier_recovery_ratio": 0.15509126412270757,
      "noise_floor_db": null,
      "defects_remaining": null,
      "anomalies": [],
      "pegelexplosion_detected": false,
      "pegelexplosion_severity": "none",
      "pegelexplosion_cause": null
    },
    {
      "phase_id": "phase_53_semantic_audio",
      "wall_time_s": 1779054129.2060928,
      "musical_goals": {
        "brillanz": 0.5912603442099348,
        "waerme": 0.9668006205821992,
        "groove": 0.4998417942889597,
        "tonal_center": 1.0,
        "natuerlichkeit": 1.0,
        "timbre_authentizitaet": 1.0,
        "bass_kraft": 1.0,
        "authentizitaet": 1.0,
        "emotionalitaet": 0.604664281936839,
        "transparenz": 0.8393559465349109,
        "spatial_depth": 0.9922910779444475,
        "micro_dynamics": 0.9429999999999996,
        "separation_fidelity": 0.8349999998928956,
        "artikulation": 0.9239999990171086
      },
      "hpi_score": 0.2601,
      "artifact_freedom": 1.0,
      "carrier_recovery_ratio": 0.15509126412270757,
      "noise_floor_db": null,
      "defects_remaining": null,
      "anomalies": [],
      "pegelexplosion_detected": false,
      "pegelexplosion_severity": "none",
      "pegelexplosion_cause": null
    },
    {
      "phase_id": "phase_37_bass_enhancement",
      "wall_time_s": 1779054140.0340548,
      "musical_goals": {
        "brillanz": 0.5912662390746958,
        "waerme": 0.9667995213636897,
        "groove": 0.4998418118319178,
        "tonal_center": 1.0,
        "natuerlichkeit": 1.0,
        "timbre_authentizitaet": 1.0,
        "bass_kraft": 1.0,
        "authentizitaet": 1.0,
        "emotionalitaet": 0.6046739905444783,
        "transparenz": 0.8393522911120384,
        "spatial_depth": 0.9924605526707134,
        "micro_dynamics": 0.9429999999999996,
        "separation_fidelity": 0.8160578441249515,
        "artikulation": 0.9239999980943852
      },
      "hpi_score": 0.2601,
      "artifact_freedom": 1.0,
      "carrier_recovery_ratio": 0.15509126412270757,
      "noise_floor_db": null,
      "defects_remaining": null,
      "anomalies": [],
      "pegelexplosion_detected": false,
      "pegelexplosion_severity": "none",
      "pegelexplosion_cause": null
    },
    {
      "phase_id": "phase_13_stereo_enhancement",
      "wall_time_s": 1779054150.578083,
      "musical_goals": {
        "brillanz": 0.5912662390746958,
        "waerme": 0.9667995213636897,
        "groove": 0.4998418118319178,
        "tonal_center": 1.0,
        "natuerlichkeit": 1.0,
        "timbre_authentizitaet": 1.0,
        "bass_kraft": 1.0,
        "authentizitaet": 1.0,
        "emotionalitaet": 0.6046739905444783,
        "transparenz": 0.8393522911120384,
        "spatial_depth": 0.9924605526707134,
        "micro_dynamics": 0.9429999999999996,
        "separation_fidelity": 0.8160578441249515,
        "artikulation": 0.9239999980943852
      },
      "hpi_score": 0.2601,
      "artifact_freedom": 1.0,
      "carrier_recovery_ratio": 0.15509126412270757,
      "noise_floor_db": null,
      "defects_remaining": null,
      "anomalies": [],
      "pegelexplosion_detected": false,
      "pegelexplosion_severity": "none",
      "pegelexplosion_cause": null
    },
    {
      "phase_id": "phase_46_spatial_enhancement",
      "wall_time_s": 1779054170.1677258,
      "musical_goals": {
        "brillanz": 0.5912898589870391,
        "waerme": 0.9667983614645107,
        "groove": 0.4998418653321302,
        "tonal_center": 1.0,
        "natuerlichkeit": 1.0,
        "timbre_authentizitaet": 1.0,
        "bass_kraft": 1.0,
        "authentizitaet": 1.0,
        "emotionalitaet": 0.6046655517667525,
        "transparenz": 0.8393556530513197,
        "spatial_depth": 0.954829298149649,
        "micro_dynamics": 0.9429999999999996,
        "separation_fidelity": 0.8205532819552406,
        "artikulation": 0.9239999587844925
      },
      "hpi_score": 0.2601,
      "artifact_freedom": 1.0,
      "carrier_recovery_ratio": 0.15509126412270757,
      "noise_floor_db": null,
      "defects_remaining": null,
      "anomalies": [],
      "pegelexplosion_detected": false,
      "pegelexplosion_severity": "none",
      "pegelexplosion_cause": null
    },
    {
      "phase_id": "phase_48_stereo_width_enhancer",
      "wall_time_s": 1779054186.3960147,
      "musical_goals": {
        "brillanz": 0.5912898426950142,
        "waerme": 0.9667983679319136,
        "groove": 0.4998418653217868,
        "tonal_center": 1.0,
        "natuerlichkeit": 1.0,
        "timbre_authentizitaet": 1.0,
        "bass_kraft": 1.0,
        "authentizitaet": 1.0,
        "emotionalitaet": 0.6046655716242089,
        "transparenz": 0.8393556329108205,
        "spatial_depth": 0.9470615357903969,
        "micro_dynamics": 0.9429999999999996,
        "separation_fidelity": 0.8205445431179654,
        "artikulation": 0.9239999977674309
      },
      "hpi_score": 0.2601,
      "artifact_freedom": 1.0,
      "carrier_recovery_ratio": 0.15509126412270757,
      "noise_floor_db": null,
      "defects_remaining": null,
      "anomalies": [],
      "pegelexplosion_detected": false,
      "pegelexplosion_severity": "none",
      "pegelexplosion_cause": null
    },
    {
      "phase_id": "phase_16_final_eq",
      "wall_time_s": 1779054197.0529578,
      "musical_goals": {
        "brillanz": 0.5912898426950142,
        "waerme": 0.9667983679319136,
        "groove": 0.4998418653217868,
        "tonal_center": 1.0,
        "natuerlichkeit": 1.0,
        "timbre_authentizitaet": 1.0,
        "bass_kraft": 1.0,
        "authentizitaet": 1.0,
        "emotionalitaet": 0.6046655716242089,
        "transparenz": 0.8393556329108205,
        "spatial_depth": 0.9470615357903969,
        "micro_dynamics": 0.9429999999999996,
        "separation_fidelity": 0.8205445431179654,
        "artikulation": 0.9239999977674309
      },
      "hpi_score": 0.2601,
      "artifact_freedom": 1.0,
      "carrier_recovery_ratio": 0.15509126412270757,
      "noise_floor_db": null,
      "defects_remaining": null,
      "anomalies": [],
      "pegelexplosion_detected": false,
      "pegelexplosion_severity": "none",
      "pegelexplosion_cause": null
    },
    {
      "phase_id": "phase_17_mastering_polish",
      "wall_time_s": 1779054213.070134,
      "musical_goals": {
        "brillanz": 0.613512370946354,
        "waerme": 0.9661975054017148,
        "groove": 0.49984600902400667,
        "tonal_center": 1.0,
        "natuerlichkeit": 1.0,
        "timbre_authentizitaet": 1.0,
        "bass_kraft": 1.0,
        "authentizitaet": 1.0,
        "emotionalitaet": 0.6057423630376203,
        "transparenz": 0.8361789909458136,
        "spatial_depth": 0.9465847113587926,
        "micro_dynamics": 0.9429999999999996,
        "separation_fidelity": 0.8154033517726956,
        "artikulation": 0.9239997400075259
      },
      "hpi_score": 0.2601,
      "artifact_freedom": 1.0,
      "carrier_recovery_ratio": 0.15509126412270757,
      "noise_floor_db": null,
      "defects_remaining": null,
      "anomalies": [],
      "pegelexplosion_detected": false,
      "pegelexplosion_severity": "none",
      "pegelexplosion_cause": null
    },
    {
      "phase_id": "phase_40_loudness_normalization",
      "wall_time_s": 1779054241.0155141,
      "musical_goals": {
        "brillanz": 0.613512370946354,
        "waerme": 0.9661975054017148,
        "groove": 0.49984600902400667,
        "tonal_center": 1.0,
        "natuerlichkeit": 1.0,
        "timbre_authentizitaet": 1.0,
        "bass_kraft": 1.0,
        "authentizitaet": 1.0,
        "emotionalitaet": 0.6057423630376203,
        "transparenz": 0.8361789909458136,
        "spatial_depth": 0.9465847113587926,
        "micro_dynamics": 0.9429999999999996,
        "separation_fidelity": 0.8154033517726956,
        "artikulation": 0.9239997400075259
      },
      "hpi_score": 0.2601,
      "artifact_freedom": 1.0,
      "carrier_recovery_ratio": 0.15509126412270757,
      "noise_floor_db": null,
      "defects_remaining": null,
      "anomalies": [],
      "pegelexplosion_detected": false,
      "pegelexplosion_severity": "none",
      "pegelexplosion_cause": null
    },
    {
      "phase_id": "phase_47_truepeak_limiter",
      "wall_time_s": 1779054258.271683,
      "musical_goals": {
        "brillanz": 0.613512370946354,
        "waerme": 0.9661975054017148,
        "groove": 0.4998459882184432,
        "tonal_center": 1.0,
        "natuerlichkeit": 1.0,
        "timbre_authentizitaet": 1.0,
        "bass_kraft": 1.0,
        "authentizitaet": 1.0,
        "emotionalitaet": 0.605761119950215,
        "transparenz": 0.8361789909458136,
        "spatial_depth": 0.9465800419914553,
        "micro_dynamics": 0.9429999999999996,
        "separation_fidelity": 0.8349999998960357,
        "artikulation": 0.9239999985333887
      },
      "hpi_score": 0.2601,
      "artifact_freedom": 1.0,
      "carrier_recovery_ratio": 0.15509126412270757,
      "noise_floor_db": null,
      "defects_remaining": null,
      "anomalies": [],
      "pegelexplosion_detected": false,
      "pegelexplosion_severity": "none",
      "pegelexplosion_cause": null
    },
    {
      "phase_id": "phase_41_output_format_optimization",
      "wall_time_s": 1779054272.584614,
      "musical_goals": {
        "brillanz": 0.613512370946354,
        "waerme": 0.9661975054017148,
        "groove": 0.4998459882184432,
        "tonal_center": 1.0,
        "natuerlichkeit": 1.0,
        "timbre_authentizitaet": 1.0,
        "bass_kraft": 1.0,
        "authentizitaet": 1.0,
        "emotionalitaet": 0.605761119950215,
        "transparenz": 0.8361789909458136,
        "spatial_depth": 0.9465800419914553,
        "micro_dynamics": 0.9429999999999996,
        "separation_fidelity": 0.8349999998960357,
        "artikulation": 0.9239999985333887
      },
      "hpi_score": 0.2601,
      "artifact_freedom": 1.0,
      "carrier_recovery_ratio": 0.15509126412270757,
      "noise_floor_db": null,
      "defects_remaining": null,
      "anomalies": [],
      "pegelexplosion_detected": false,
      "pegelexplosion_severity": "none",
      "pegelexplosion_cause": null
    },
    {
      "phase_id": "phase_15_stereo_balance",
      "wall_time_s": 1779054281.7391188,
      "musical_goals": {
        "brillanz": 0.6133637862699509,
        "waerme": 0.9662146369912348,
        "groove": 0.49984591906840536,
        "tonal_center": 1.0,
        "natuerlichkeit": 1.0,
        "timbre_authentizitaet": 1.0,
        "bass_kraft": 1.0,
        "authentizitaet": 1.0,
        "emotionalitaet": 0.6057177935745423,
        "transparenz": 0.8362399939057215,
        "spatial_depth": 0.9465770507397339,
        "micro_dynamics": 0.9429999999999996,
        "separation_fidelity": 0.8278582554995728,
        "artikulation": 0.9239999977100622
      },
      "hpi_score": 0.2601,
      "artifact_freedom": 1.0,
      "carrier_recovery_ratio": 0.15509126412270757,
      "noise_floor_db": null,
      "defects_remaining": null,
      "anomalies": [],
      "pegelexplosion_detected": false,
      "pegelexplosion_severity": "none",
      "pegelexplosion_cause": null
    }
  ],
  "final_musical_goals": {
    "bass_kraft": 1.0,
    "brillanz": 0.4315994658863744,
    "waerme": 0.5793303209455373,
    "natuerlichkeit": 0.9417832532211134,
    "authentizitaet": 1.0,
    "emotionalitaet": 0.8287427553441375,
    "transparenz": 0.2437852945048527,
    "groove": 0.9499999999992998,
    "spatial_depth": 0.5371113051913852,
    "timbre_authentizitaet": 1.0,
    "tonal_center": 0.9999999974174174,
    "micro_dynamics": 1.0,
    "separation_fidelity": 0.9999999987147672,
    "artikulation": 0.9999999964123484
  },
  "anomalies": [],
  "summary": {
    "total_phases": 41,
    "total_anomalies": 0,
    "final_hpi": 0.2601,
    "final_artifact_freedom": 1.0,
    "p1_avg_score": 0.9708916266105567,
    "p1_source": "final_musical_goals",
    "quality_status": "EXCELLENT"
  }
}
